tofile/__init__.py
tofile/main.py
tofile-0.1.0.dist-info/LICENSE
tofile-0.1.0.dist-info/METADATA
tofile-0.1.0.dist-info/WHEEL
tofile-0.1.0.dist-info/entry_points.txt
tofile-0.1.0.dist-info/top_level.txt
tofile-0.1.0.dist-info/RECORD
