Metadata-Version: 2.1
Name: tofile
Version: 0.1.0
Summary: Create directory structures from tree command output
Home-page: https://github.com/dawid-ai/tree2file
Author: dawid-ai
Author-email: dawid-ai <hello@dawid.ai>
License: MIT
Project-URL: Homepage, https://github.com/dawid-ai/tree2file
Project-URL: Bug Tracker, https://github.com/dawid-ai/tree2file/issues
Classifier: Programming Language :: Python :: 3
Classifier: License :: OSI Approved :: MIT License
Classifier: Operating System :: OS Independent
Classifier: Environment :: Console
Classifier: Topic :: Utilities
Requires-Python: >=3.6
License-File: LICENSE
